Workbook

Sheet README
A1: AgrosTech — Financial Model v2.0
A3: How to use this workbook
A4: • Yellow cells = [CONFIRM]: placeholder assumptions the founder needs to validate before this leaves internal use.
A5: • Green cells = assumption inputs that drive formulas elsewhere — change these, not the formula cells, to update the model.
A6: • v2.0: reconciled against the founder's pitch deck (AgrosTech_Pitch_Narrativo.pdf, 2026-09-24). USD is now the primary currency throughout (the SAFE is a US-dollar instrument) — R$ shown as a secondary reference at an assumed ~R$5.00/US$1.
A7: • Core confirmed numbers: US$0.80/ha/year subscription (Passaporte de Crédito Rural) + one-off survey services; US$600,000 raise at a US$4,000,000 post-money cap (15%), 4yr vesting/1yr cliff.
A8: • It intentionally does NOT use the older R$35-120/ha drone-mission pricing in knowledge-base/PRICING_MODEL.md — that belonged to a prior services-only version of the business model.
A9: • Tabs: Hypotheses -> 'Scenarios (Deck)' [the OFFICIAL forecast, taken directly from the pitch deck] -> Unit Economics -> Pipeline -> Actuals -> Budget (18mo) [a supporting bottom-up build, see its own note] -> Scenarios (Bottom-Up) -> Cap Table -> Use of Funds.
A10: • 'Scenarios (Deck)' is the number to lead with in investor conversations — it's the founder's own stated forecast. The 'Budget (Base)' / 'Scenarios (Bottom-Up)' tabs are an independent monthly build from named pipeline + cost assumptions, useful as a sanity check and for burn/runway planning, but on a different time basis (rolling 18mo from raise-close vs. calendar year) — the two are not expected to match exactly, and that's noted on both tabs.

Sheet Hypotheses
A1: Hypotheses Behind the Model
A3: Per the checklist: "the assumptions behind each scenario, written out so they can be challenged." Every number in Budget/Scenarios traces back to one of these rows.
A5: # | B5: Hypothesis | C5: Base case value | D5: Bull case | E5: Bear case | F5: Confidence | G5: Why
A6: 1 | B6: Subscription price | C6: US$ 0.80/ha/year (≈R$4.00) | D6: US$ 0.80/ha/year (unchanged) | E6: US$ 0.64/ha/year (-20%, price pressure) | F6: High | G6: Confirmed by founder and by the deck's 'O Mercado' slide
A7: 2 | B7: Avg. one-off survey fee | C7: R$ 15,000 | D7: R$ 20,000/survey | E7: R$ 12,000/survey | F7: Medium | G7: No confirmed figure exists for the current model; needs founder input from actual quotes
A8: 3 | B8: Monthly new hectares added (base) | C8: 500 ha/mo, ramping +10%/mo | D8: 1.75x this rate | E8: 0.5x this rate | F8: Low — placeholder ramp | G8: No historical cohort exists yet to calibrate off
A9: 4 | B9: Pipeline conversion — Coplacana | C9: 50000 | D9: Converts in full by M6 | E9: Does not convert in 18mo window | F9: Low | G9: Named account, terms unconfirmed
A10: 5 | B10: Pipeline conversion — Thales (~30,000 ha cacao, Bahia, 200+ producers) + unnamed global trading/barter manager (deck's combined figure: 35,000 ha) | C10: 20% converts by M12 | D10: 60% converts by M9 | E10: 5% converts (consultant relationship stalls) | F10: Low | G10: Consultant relationship, not direct producer — conversion probability especially uncertain; see Pipeline tab for the two-contact reconciliation
A11: 6 | B11: Gross margin — subscription | C11: 0.7 | D11: 85% | E11: 70% | F11: Medium | G11: Subscription COGS = data/API/cloud costs, low marginal cost per hectare once pipeline exists
A12: 7 | B12: Gross margin — survey services | C12: 0.55 | D12: 60% | E12: 45% | F12: Low | G12: Placeholder; needs real COGS build (pilot cost, processing, travel) once model isn't reusing the old per-ha cost table
A13: 8 | B13: Monthly churn (subscription) | C13: 2%/mo | D13: 1%/mo | E13: 5%/mo | F13: Low | G13: No renewal cohort exists yet to measure
A14: 9 | B14: Team headcount growth | C14: Per Hiring Plan: CTO M1-2, data engineer M3-4, sales M4-6 | D14: Same, faster ramp | E14: CTO hire delayed to M4 | F14: Medium | G14: Sequencing confirmed by founder; exact timing not yet
A15: 10 | B15: Founder/existing team comp | C15: Monthly pro-labore/salary for Amgad, Diana, Lucas | D15: — | E15: — | F15: Low | G15: Not yet provided
A16: 11 | B16: Base-case driver for the deck's official 2027-2029 forecast | C16: ~8 cooperativas (cooperative-scale accounts) by 2028, at US$0.80/ha | D16: More/larger accounts, faster | E16: Fewer/smaller accounts, slower | F16: Low — deck's own stated assumption, not independently modeled bottom-up | G16: Directly from the deck's revenue-scenario slide footnote; see 'Scenarios (Deck)' tab

Sheet Scenarios (Deck)
A1: Scenarios — Official Forecast (from the Pitch Deck)
A5: Basis (per the deck's own footnote) | B5: US$ 0.80/ha and ~8 cooperativas (cooperative-scale accounts) in 2028. Projections, not results.
A7: Year | B7: Pessimista (US$M) | C7: Base (US$M) | D7: Otimista (US$M)
A8: 2027 | B8: 0.18 | C8: 0.38 | D8: 0.58
A9: 2028 | B9: 0.66 | C9: 1.32 | D9: 2
A10: 2029 | B10: 1.6 | C10: 3.5 | D10: 4.56
A12: Implied CAGR 2027→2029 (Base) | B12: =(C10/C8)^(1/2)-1
A19: The 36-month target (US$3M, stated on the market-sizing slide) and the 2029 Base-case revenue projection (US$3.50M, stated on the scenarios slide) are close but not identical — both are the founder's own numbers from two different slides of the same deck, not a discrepancy this data room introduced. Worth a quick founder gut-check on which framing to lead with (a single target figure vs. the full scenario table), but not a red flag requiring reconciliation.

Sheet Unit Economics
A1: Unit Economics
A5: Subscription (Passaporte de Crédito Rural)
A6: Price per ha/year (US$) | B6: 0.8
A7: Gross margin % | B7: 0.7
A8: Gross profit per ha/year | B8: =B6*B7
A9: Avg. hectares per customer | B9: 1500
A10: Annual revenue per customer | B10: =B6*B9
A11: Annual gross profit per customer | B11: =B7*B10
A12: Monthly churn | B12: 0.02
A13: Implied avg. customer lifetime (months) | B13: =1/B12
A14: LTV (gross profit basis) | B14: =B11/12*B13
A16: Survey services (one-off)
A17: Avg. fee per survey (US$) | B17: 3000
A18: Gross margin % | B18: 0.55
A19: Gross profit per survey | B19: =B17*B18
A21: CAC (placeholder — [CONFIRM])
A22: Estimated CAC per subscription customer | B22: 6000
A24: LTV : CAC ratio | B24: =B14/B22 | C24: =IF(B24<1,"CAC EXCEEDS LTV — losing money per customer at these assumptions",IF(B24<3,"Below the ~3x healthy-SaaS benchmark","Healthy"))

Sheet Pipeline
A1: Sales Pipeline
A5: Account | B5: Type | C5: Hectares | D5: Stage [CONFIRM] | E5: Probability [CONFIRM] | F5: Target close (month #) [CONFIRM] | G5: Annual subscription value (ha x US$0.80)
A6: Coplacana | B6: Cooperative | C6: 5000000 | D6: Intial conversations | E6: 0.05 | F6: M14 | G6: =C6*0.8
A7: Thales — cacao consultant, Bahia, 200+ producers | B7: Consultant / channel | C7: 30000 | D7: Expressed interest | E7: 0.2 | F7: M4 | G7: =C7*0.8
A8: [Global trading/barter manager — unnamed, per deck] | B8: Consultant / channel | C8: 500000 | D8: Case study | E8: 0.1 | F8: M8 | G8: =C8*0.8
A9: [Other pipeline accounts] | B9: Bradesco, itau | C9: 100000 | D9: Intial conversations | E9: 0.05 | F9: M12 | G9: =C9*0.8
A10: Total (named pipeline, illustrative) | C10: =SUM(C6:C9) | G10: =SUM(G6:G9)
A12: Cross-check: pipeline annual value vs. deck's own 2029 Base case (Scenarios (Deck)!C10, US$M) | G12: =G10/1000000 | H12: ='Scenarios (Deck)'!C10 | I12: =IF(G12>H12,"Pipeline alone exceeds the deck's entire 2029 target — check for a units/scale error in Hectares (col C)","OK")

Sheet Actuals
A1: Actuals to Date
A5: Date | B5: Client | C5: Engagement | D5: Type | E5: Hectares | F5: Amount (US$) | G5: Status
A6: 46030 | B6: Fabio | C6: CAR/SICAR georeferencing survey, Minas Gerais | D6: One-off survey | E6: 220 | F6: 1400 | G6: Delivered & paid — generated retention and scope renegotiation (per deck)
A7: 21/08/2026 | B7: X | C7: 35 ha weed-stress scan (10 ha affected) | D7: One-off survey | E7: 35 | F7: 180 | G7: Delivered & paid — generated retention and scope renegotiation (per deck)
A8: Total revenue to date | F8: =SUM(F6:F7)
A10: Cash & burn to date
A11: Cash in bank today | B11: 200
A12: Avg. monthly burn to date | B12: 5
A13: Runway at current burn (months) | B13: =B11/B12

Sheet Budget (Base)
A1: 18-Month Budget — Bottom-Up Build
A5: Driver / Line item | B5: M1 | C5: M2 | D5: M3 | E5: M4 | F5: M5 | G5: M6 | H5: M7 | I5: M8 | J5: M9 | K5: M10 | L5: M11 | M5: M12 | N5: M13 | O5: M14 | P5: M15 | Q5: M16 | R5: M17 | S5: M18
A6: Cumulative hectares under subscription | B6: 500 | C6: =B6+500*(1.1^1) | D6: =C6+500*(1.1^2) | E6: =D6+500*(1.1^3) | F6: =E6+500*(1.1^4) | G6: =F6+500*(1.1^5) | H6: =G6+500*(1.1^6) | I6: =H6+500*(1.1^7) | J6: =I6+500*(1.1^8) | K6: =J6+500*(1.1^9) | L6: =K6+500*(1.1^10) | M6: =L6+500*(1.1^11) | N6: =M6+500*(1.1^12) | O6: =N6+500*(1.1^13) | P6: =O6+500*(1.1^14) | Q6: =P6+500*(1.1^15) | R6: =Q6+500*(1.1^16) | S6: =R6+500*(1.1^17)
A7: New surveys delivered this month | B7: =ROUND(2+(1-1)*0.24,0) | C7: =ROUND(2+(2-1)*0.24,0) | D7: =ROUND(2+(3-1)*0.24,0) | E7: =ROUND(2+(4-1)*0.24,0) | F7: =ROUND(2+(5-1)*0.24,0) | G7: =ROUND(2+(6-1)*0.24,0) | H7: =ROUND(2+(7-1)*0.24,0) | I7: =ROUND(2+(8-1)*0.24,0) | J7: =ROUND(2+(9-1)*0.24,0) | K7: =ROUND(2+(10-1)*0.24,0) | L7: =ROUND(2+(11-1)*0.24,0) | M7: =ROUND(2+(12-1)*0.24,0) | N7: =ROUND(2+(13-1)*0.24,0) | O7: =ROUND(2+(14-1)*0.24,0) | P7: =ROUND(2+(15-1)*0.24,0) | Q7: =ROUND(2+(16-1)*0.24,0) | R7: =ROUND(2+(17-1)*0.24,0) | S7: =ROUND(2+(18-1)*0.24,0)
A9: Revenue
A10: Subscription revenue (monthly recognition of US$0.80/ha/yr) | B10: =B6*'Unit Economics'!$B$6/12 | C10: =C6*'Unit Economics'!$B$6/12 | D10: =D6*'Unit Economics'!$B$6/12 | E10: =E6*'Unit Economics'!$B$6/12 | F10: =F6*'Unit Economics'!$B$6/12 | G10: =G6*'Unit Economics'!$B$6/12 | H10: =H6*'Unit Economics'!$B$6/12 | I10: =I6*'Unit Economics'!$B$6/12 | ... S10: =S6*'Unit Economics'!$B$6/12
A11: Survey services revenue | B11: =B7*'Unit Economics'!$B$17 | C11: =C7*'Unit Economics'!$B$17 | D11: =D7*'Unit Economics'!$B$17 | E11: =E7*'Unit Economics'!$B$17 | F11: =F7*'Unit Economics'!$B$17 | G11: =G7*'Unit Economics'!$B$17 | H11: =H7*'Unit Economics'!$B$17 | I11: =I7*'Unit Economics'!$B$17 | ... S11: =S7*'Unit Economics'!$B$17
A12: TOTAL REVENUE | B12: =B10+B11 | C12: =C10+C11 | D12: =D10+D11 | E12: =E10+E11 | F12: =F10+F11 | G12: =G10+G11 | H12: =H10+H11 | I12: =I10+I11 | ... S12: =S10+S11
A14: Gross profit
A15: Gross profit | B15: =B10*'Unit Economics'!$B$7+B11*'Unit Economics'!$B$18 | C15: =C10*'Unit Economics'!$B$7+C11*'Unit Economics'!$B$18 | D15: =D10*'Unit Economics'!$B$7+D11*'Unit Economics'!$B$18 | E15: =E10*'Unit Economics'!$B$7+E11*'Unit Economics'!$B$18 | F15: =F10*'Unit Economics'!$B$7+F11*'Unit Economics'!$B$18 | G15: =G10*'Unit Economics'!$B$7+G11*'Unit Economics'!$B$18 | H15: =H10*'Unit Economics'!$B$7+H11*'Unit Economics'!$B$18 | I15: =I10*'Unit Economics'!$B$7+I11*'Unit Economics'!$B$18 | ... S15: =S10*'Unit Economics'!$B$7+S11*'Unit Economics'!$B$18
A17: Operating costs, US$/month [CONFIRM all — placeholders below, sized against the $600K raise]
A18: Founder comp (Amgad, Diana, Lucas combined), US$ [CONFIRM] | B18: 3000 | C18: 3000 | D18: 3000 | E18: 3000 | F18: 3000 | G18: 3000 | H18: 3000 | I18: 3000 | J18: 3000 | K18: 3000 | L18: 3000 | M18: 3000 | N18: 3000 | O18: 3000 | P18: 3000 | Q18: 3000 | R18: 3000 | S18: 3000
A19: CTO hire (from M2), US$ [CONFIRM] | B19: 0 | C19: 2400 | D19: 2400 | E19: 2400 | F19: 2400 | G19: 2400 | H19: 2400 | I19: 2400 | J19: 2400 | K19: 2400 | L19: 2400 | M19: 2400 | N19: 2400 | O19: 2400 | P19: 2400 | Q19: 2400 | R19: 2400 | S19: 2400
A20: Geospatial/data engineer (from M4), US$ | B20: 0 | C20: 0 | D20: 0 | E20: 1800 | F20: 1800 | G20: 1800 | H20: 1800 | I20: 1800 | J20: 1800 | K20: 1800 | L20: 1800 | M20: 1800 | N20: 1800 | O20: 1800 | P20: 1800 | Q20: 1800 | R20: 1800 | S20: 1800
A21: Sales hire (from M5), US$ [CONFIRM] | B21: 0 | C21: 0 | D21: 0 | E21: 0 | F21: 1600 | G21: 1600 | H21: 1600 | I21: 1600 | J21: 1600 | K21: 1600 | L21: 1600 | M21: 1600 | N21: 1600 | O21: 1600 | P21: 1600 | Q21: 1600 | R21: 1600 | S21: 1600
A22: Data/infra (satellite APIs, cloud, MapBiomas-class data), US$ | B22: 600 | C22: 600 | D22: 600 | E22: 600 | F22: 600 | G22: 600 | H22: 600 | I22: 600 | J22: 600 | K22: 600 | L22: 600 | M22: 600 | N22: 600 | O22: 600 | P22: 600 | Q22: 600 | R22: 600 | S22: 600
A23: Legal & entity setup — Delaware + Brazilian LTDA formation (front-loaded M1-M3), US$ | B23: 1000 | C23: 1000 | D23: 1000 | E23: 0 | F23: 0 | G23: 0 | H23: 0 | I23: 0 | J23: 0 | K23: 0 | L23: 0 | M23: 0 | N23: 0 | O23: 0 | P23: 0 | Q23: 0 | R23: 0 | S23: 0
A24: G&A / other, US$ | B24: 800 | C24: 800 | D24: 800 | E24: 800 | F24: 800 | G24: 800 | H24: 800 | I24: 800 | J24: 800 | K24: 800 | L24: 800 | M24: 800 | N24: 800 | O24: 800 | P24: 800 | Q24: 800 | R24: 800 | S24: 800
A25: TOTAL OPERATING COSTS | B25: =SUM(B18:B24) | C25: =SUM(C18:C24) | D25: =SUM(D18:D24) | E25: =SUM(E18:E24) | F25: =SUM(F18:F24) | G25: =SUM(G18:G24) | H25: =SUM(H18:H24) | I25: =SUM(I18:I24) | ... S25: =SUM(S18:S24)
A27: Cash flow & runway
A28: Net burn (gross profit − opex) | B28: =B15-B25 | C28: =C15-C25 | D28: =D15-D25 | E28: =E15-E25 | F28: =F15-F25 | G28: =G15-G25 | H28: =H15-H25 | I28: =I15-I25 | ... S28: =S15-S25
A29: Cash balance, US$ (starting: US$600,000 raise) | B29: =600000+B28 | C29: =B29+C28 | D29: =C29+D28 | E29: =D29+E28 | F29: =E29+F28 | G29: =F29+G28 | H29: =G29+H28 | I29: =H29+I28 | J29: =I29+J28 | ... S29: =R29+S28
A30: Runway remaining (months, at trailing burn) [CONFIRM once burn stabilizes] | B30: =IF(B28>=0,"n/a (cash flow positive)",-B29/B28) | C30: =IF(C28>=0,"n/a (cash flow positive)",-C29/C28) | D30: =IF(D28>=0,"n/a (cash flow positive)",-D29/D28) | E30: =IF(E28>=0,"n/a (cash flow positive)",-E29/E28) | F30: =IF(F28>=0,"n/a (cash flow positive)",-F29/F28) | G30: =IF(G28>=0,"n/a (cash flow positive)",-G29/G28) | H30: =IF(H28>=0,"n/a (cash flow positive)",-H29/H28) | I30: =IF(I28>=0,"n/a (cash flow positive)",-I29/I28) | ... S30: =IF(S28>=0,"n/a (cash flow positive)",-S29/S28)

Sheet Scenarios (Bottom-Up)
A1: Scenarios (Bottom-Up) — Bull / Base / Bear
A5: Scenario multipliers
A6: Scenario | B6: Hectare-growth multiplier | C6: Survey-volume multiplier | D6: Note
A7: Bear | B7: 0.5 | C7: 0.7 | D7: Pipeline conversion stalls; Thales relationship doesn't convert
A8: Base | B8: 1 | C8: 1 | D8: Matches Budget (Base) tab exactly
A9: Bull | B9: 1.75 | C9: 1.4 | D9: Coplacana + majority of Thales' 30,000 ha convert within 12mo
A11: 18-month outcomes (computed)
A12: Scenario | B12: Month-18 hectares | C12: Total 18mo revenue (US$) | D12: Cash balance at M18 (US$) | E12: Cash-flow positive by month?
A13: Bear | B13: =ROUND('Budget (Base)'!S6*B7,0) | C13: =SUM('Budget (Base)'!B12:S12)*((B7+C7)/2) | D13: =600000+C13-(AVERAGE('Budget (Base)'!B25:S25)*18) | E13: Illustrative — see note
A14: Base | B14: ='Budget (Base)'!S6 | C14: =SUM('Budget (Base)'!B12:S12) | D14: ='Budget (Base)'!S29 | E14: See Budget tab, row 'Runway remaining'
A15: Bull | B15: =ROUND('Budget (Base)'!S6*B9,0) | C15: =SUM('Budget (Base)'!B12:S12)*((B9+C9)/2) | D15: =600000+C15-(AVERAGE('Budget (Base)'!B25:S25)*18) | E15: Illustrative — see note

Sheet Cap Table
A1: Cap Table
A5: SAFE mechanics (confirmed by pitch deck's ask slide)
A6: Raise (US$) | B6: 600000
A7: Post-money valuation cap (US$) | B7: 4000000
A8: SAFE holders' post-money % | B8: =B6/B7
A9: Option pool % | B9: 0.1
A10: Remaining for founders % | B10: =1-B8-B9
A12: Founder split (of the 'remaining for founders' pool) [CONFIRM — equal-thirds placeholder]
A13: Founder | B13: Pre-SAFE illustrative split | C13: Post-SAFE %
A14: Amgad | B14: 0.7 | C14: =B14*$B$10
A15: Diana Dutra | B15: 0.1 | C15: =B15*$B$10
A16: Lucas Costa | B16: 0.08 | C16: =B16*$B$10
A17: Checksum — do B14:B16 sum to 100%? | B17: =SUM(B14:B16) | C17: =IF(ABS(B17-1)<0.0001,"OK","MISMATCH — see B18")
A18: Unallocated founder equity [CONFIRM WITH FOUNDER — not assumed] | B18: =1-B17 | C18: =B18*$B$10
A19: SAFE holders (class) | C19: =B8
A20: Option pool | C20: =B9
A21: TOTAL | C21: =SUM(C14:C20) | D21: =IF(ABS(C21-1)<0.0001,"OK — sums to 100%","STILL BROKEN — check inputs")

Sheet Use of Funds
A1: Use of Funds
A5: Total raise (US$) | B5: 600000
A7: Category | B7: % of raise | C7: US$
A8: Dados e IA (Data, platform, hardware & AI — the M1/M2/M3 model stack) | B8: 0.4 | C8: =B8*$B$5
A9: Vendas institucionais (Institutional sales — banks, cooperatives, credit desks) | B9: 0.3 | C9: =B9*$B$5
A10: Operações e reserva (Operations & reserve) | B10: 0.2 | C10: =B10*$B$5
A11: Integrações Bacen e segurança (Bacen integrations & security) | B11: 0.1 | C11: =B11*$B$5
A12: TOTAL | B12: =SUM(B8:B11) | C12: =SUM(C8:C11)
